[
  {
    "title": "【限定セットアイテム】ゴールドツイストチェーンネックレスセット※定価546万円(税込)相当※",
    "source_product_id": "xxxxx-250222-0700",
    "product_url": "https://www.rinkan-online.com/products/xxxxx-250222-0700",
    "main_image_url": "https://cdn.rinkan-online.com/images/xxxxx-250222-0700_1.jpg",
    "image_urls": [
      "https://cdn.rinkan-online.com/images/xxxxx-250222-0700_1.jpg",
      "https://cdn.rinkan-online.com/images/xxxxx-250222-0700_2.jpg",
      "https://cdn.rinkan-online.com/images/xxxxx-250222-0700_3.jpg",
      "https://cdn.rinkan-online.com/images/xxxxx-250222-0700_4.jpg",
      "https://cdn.rinkan-online.com/images/xxxxx-250222-0700_5.jpg",
      "https://cdn.rinkan-online.com/images/xxxxx-250222-0700_6.jpg",
      "https://cdn.rinkan-online.com/images/xxxxx-250222-0700_7.jpg"
    ],
    "price_original": 5000000,
    "currency_code": "JPY",
    "brand_name": "Chrome Hearts",
    "gender_label": "メンズ",
    "general_category_name": "accessories",
    "category_name": "accessory",
    "subcategory_name": "ペンダントトップ",
    "condition_rank": "B",
    "size_label": "18inch",
    "measurements_text": "ファットクロス横1.7cm,ファットクロス縦3.4cm,フィリグリー横1.9cm,フィリグリー縦3.1cm,ベイビーファット横1cm,ベイビーファット縦2.3cm,チェーン全長46.5cm",
    "description": "素材: 22K\n付属品: 国内配送の場合RINKAN購入証明書が付属します。※状態ランクC以下、シルバー・ゴールドパーツのない商品は除く\nその他特徴: ※単品購入よりかなりお買い得な、ネックレスチェーン+トップ×3のセット限定価格となっております※",
    "parsed_at": "2026-04-16T00:42:03.805703+00:00"
  },
  {
    "title": "【限定セットアイテム】PAVEダイヤネックレスセット※定価212万円(税込)相当※",
    "source_product_id": "xxxxx-251121-0700",
    "product_url": "https://www.rinkan-online.com/products/xxxxx-251121-0700",
    "main_image_url": "https://cdn.rinkan-online.com/images/xxxxx-251121-0700_1.jpg",
    "image_urls": [
      "https://cdn.rinkan-online.com/images/xxxxx-251121-0700_1.jpg",
      "https://cdn.rinkan-online.com/images/xxxxx-251121-0700_2.jpg",
      "https://cdn.rinkan-online.com/images/xxxxx-251121-0700_3.jpg",
      "https://cdn.rinkan-online.com/images/xxxxx-251121-0700_4.jpg",
      "https://cdn.rinkan-online.com/images/xxxxx-251121-0700_5.jpg",
      "https://cdn.rinkan-online.com/images/xxxxx-251121-0700_6.jpg",
      "https://cdn.rinkan-online.com/images/xxxxx-251121-0700_7.jpg"
    ],
    "price_original": 1950000,
    "currency_code": "JPY",
    "brand_name": "Chrome Hearts",
    "gender_label": "メンズ",
    "general_category_name": "accessories",
    "category_name": "accessory",
    "subcategory_name": "ペンダントトップ",
    "condition_rank": "B",
    "size_label": "20inch",
    "measurements_text": "(モチーフ1)横1.0cm,縦2.2cm,(モチーフ2)横1.2cm,縦2.4cm,(モチーフ3)横1.7cm,縦3.3cm,チェーン幅0.2cm,全長51.5cm",
    "description": "素材: 925\n付属品: 国内配送の場合RINKAN購入証明書が付属します。※状態ランクC以下、シルバー・ゴールドパーツのない商品は除く\nその他特徴: ※単品購入よりかなりお買い得な、ネックレスチェーン+トップ×3のセット限定価格となっております※",
    "parsed_at": "2026-04-16T00:42:06.471354+00:00"
  },
  {
    "title": "【限定セットアイテム】PAVEダイヤロールチェーンセット※定価116万円(税込)相当※",
    "source_product_id": "xxxxx-260317-0701",
    "product_url": "https://www.rinkan-online.com/products/xxxxx-260317-0701",
    "main_image_url": "https://cdn.rinkan-online.com/images/xxxxx-260317-0701_1.jpg",
    "image_urls": [
      "https://cdn.rinkan-online.com/images/xxxxx-260317-0701_1.jpg",
      "https://cdn.rinkan-online.com/images/xxxxx-260317-0701_2.jpg",
      "https://cdn.rinkan-online.com/images/xxxxx-260317-0701_3.jpg",
      "https://cdn.rinkan-online.com/images/xxxxx-260317-0701_4.jpg",
      "https://cdn.rinkan-online.com/images/xxxxx-260317-0701_5.jpg",
      "https://cdn.rinkan-online.com/images/xxxxx-260317-0701_6.jpg",
      "https://cdn.rinkan-online.com/images/xxxxx-260317-0701_7.jpg"
    ],
    "price_original": 1050000,
    "currency_code": "JPY",
    "brand_name": "Chrome Hearts",
    "gender_label": "メンズ",
    "general_category_name": "accessories",
    "category_name": "accessory",
    "subcategory_name": "ペンダントトップ",
    "condition_rank": "B",
    "size_label": null,
    "measurements_text": "クロス横0.9cm,クロス縦2.4cm,ドッグタグ横0.9cm,ドッグタグ縦2.2cm,チェーン全長46cm",
    "description": "素材: 925\n付属品: 国内配送の場合RINKAN購入証明書が付属します。※状態ランクC以下、シルバー・ゴールドパーツのない商品は除く\nその他特徴: ※単品購入よりかなりお買い得な、ネックレスチェーン+トップ×2のセット限定価格となっております※",
    "parsed_at": "2026-04-16T00:42:07.398497+00:00"
  },
  {
    "title": "【限定セットアイテム】PAVEダイヤツイストチェーンセット※定価386万円(税込)相当※",
    "source_product_id": "xxxxx-260108-0700",
    "product_url": "https://www.rinkan-online.com/products/xxxxx-260108-0700",
    "main_image_url": "https://cdn.rinkan-online.com/images/xxxxx-260108-0700_1.jpg",
    "image_urls": [
      "https://cdn.rinkan-online.com/images/xxxxx-260108-0700_1.jpg",
      "https://cdn.rinkan-online.com/images/xxxxx-260108-0700_2.jpg",
      "https://cdn.rinkan-online.com/images/xxxxx-260108-0700_3.jpg",
      "https://cdn.rinkan-online.com/images/xxxxx-260108-0700_4.jpg",
      "https://cdn.rinkan-online.com/images/xxxxx-260108-0700_5.jpg",
      "https://cdn.rinkan-online.com/images/xxxxx-260108-0700_6.jpg",
      "https://cdn.rinkan-online.com/images/xxxxx-260108-0700_7.jpg"
    ],
    "price_original": 3550000,
    "currency_code": "JPY",
    "brand_name": "Chrome Hearts",
    "gender_label": "メンズ",
    "general_category_name": "accessories",
    "category_name": "accessory",
    "subcategory_name": "ペンダントトップ",
    "condition_rank": "B",
    "size_label": "20inch",
    "measurements_text": "モチーフ1横0.9cm,縦2.3cm,モチーフ2横0.9cm,縦2.2cm,モチーフ3横0.7cm,縦1.7cm,チェーン幅0.2cm,全長51.2cm",
    "description": "素材: 22K\n付属品: 国内配送の場合RINKAN購入証明書が付属します。※状態ランクC以下、シルバー・ゴールドパーツのない商品は除く\nその他特徴: ※単品購入よりかなりお買い得な、ネックレスチェーン+トップ×3のセット限定価格となっております※",
    "parsed_at": "2026-04-16T00:42:08.334018+00:00"
  },
  {
    "title": "CHクロス装飾クロスパッチデストロイレザーショルダーバッグ【test】",
    "source_product_id": "15052-260206-0059",
    "product_url": "https://www.rinkan-online.com/products/15052-260206-0059",
    "main_image_url": "https://cdn.rinkan-online.com/images/15052-260206-0059_1.jpg",
    "image_urls": [
      "https://cdn.rinkan-online.com/images/15052-260206-0059_1.jpg",
      "https://cdn.rinkan-online.com/images/15052-260206-0059_2.jpg",
      "https://cdn.rinkan-online.com/images/15052-260206-0059_3.jpg",
      "https://cdn.rinkan-online.com/images/15052-260206-0059_4.jpg",
      "https://cdn.rinkan-online.com/images/15052-260206-0059_5.jpg"
    ],
    "price_original": 572000,
    "currency_code": "JPY",
    "brand_name": "Chrome Hearts",
    "gender_label": "メンズ",
    "general_category_name": "bags",
    "category_name": "bag",
    "subcategory_name": "ショルダーバッグ",
    "condition_rank": "B",
    "size_label": null,
    "measurements_text": "横24.5cm,縦31cm,マチ5.5cm,肩紐118cm",
    "description": "素材: 表記なし\n付属品: 国内配送の場合RINKAN購入証明書が付属します。※状態ランクC以下、シルバー・ゴールドパーツのない商品は除く",
    "parsed_at": "2026-04-16T00:42:09.113412+00:00"
  },
  {
    "title": "シルバーウォレットチェーン",
    "source_product_id": "15164-260310-0345",
    "product_url": "https://www.rinkan-online.com/products/15164-260310-0345",
    "main_image_url": "https://cdn.rinkan-online.com/images/15164-260310-0345_1.jpg",
    "image_urls": [
      "https://cdn.rinkan-online.com/images/15164-260310-0345_1.jpg",
      "https://cdn.rinkan-online.com/images/15164-260310-0345_2.jpg",
      "https://cdn.rinkan-online.com/images/15164-260310-0345_3.jpg",
      "https://cdn.rinkan-online.com/images/15164-260310-0345_4.jpg",
      "https://cdn.rinkan-online.com/images/15164-260310-0345_5.jpg"
    ],
    "price_original": 1133000,
    "currency_code": "JPY",
    "brand_name": "Chrome Hearts",
    "gender_label": "メンズ",
    "general_category_name": "accessories",
    "category_name": "accessory",
    "subcategory_name": "ウォレットチェーン",
    "condition_rank": "B",
    "size_label": "ロング",
    "measurements_text": "チェーン幅1.1cm,全長61cm",
    "description": "素材: 925\n付属品: 国内配送の場合RINKAN購入証明書が付属します。※状態ランクC以下、シルバー・ゴールドパーツのない商品は除く",
    "parsed_at": "2026-04-16T00:42:09.828819+00:00"
  },
  {
    "title": "シルバーウォレットチェーン",
    "source_product_id": "15164-251226-0374",
    "product_url": "https://www.rinkan-online.com/products/15164-251226-0374",
    "main_image_url": "https://cdn.rinkan-online.com/images/15164-251226-0374_1.jpg",
    "image_urls": [
      "https://cdn.rinkan-online.com/images/15164-251226-0374_1.jpg",
      "https://cdn.rinkan-online.com/images/15164-251226-0374_2.jpg",
      "https://cdn.rinkan-online.com/images/15164-251226-0374_3.jpg",
      "https://cdn.rinkan-online.com/images/15164-251226-0374_4.jpg",
      "https://cdn.rinkan-online.com/images/15164-251226-0374_5.jpg"
    ],
    "price_original": 1359600,
    "currency_code": "JPY",
    "brand_name": "Chrome Hearts",
    "gender_label": "メンズ",
    "general_category_name": "accessories",
    "category_name": "accessory",
    "subcategory_name": "ウォレットチェーン",
    "condition_rank": "C",
    "size_label": "ロング",
    "measurements_text": "全長50.5cm",
    "description": "素材: 925\n付属品: 国内配送の場合RINKAN購入証明書が付属します。※状態ランクC以下、シルバー・ゴールドパーツのない商品は除く",
    "parsed_at": "2026-04-16T00:42:10.597477+00:00"
  },
  {
    "title": "シルバーネックレス",
    "source_product_id": "15161-260401-0234",
    "product_url": "https://www.rinkan-online.com/products/15161-260401-0234",
    "main_image_url": "https://cdn.rinkan-online.com/images/15161-260401-0234_1.jpg",
    "image_urls": [
      "https://cdn.rinkan-online.com/images/15161-260401-0234_1.jpg",
      "https://cdn.rinkan-online.com/images/15161-260401-0234_2.jpg",
      "https://cdn.rinkan-online.com/images/15161-260401-0234_3.jpg",
      "https://cdn.rinkan-online.com/images/15161-260401-0234_4.jpg",
      "https://cdn.rinkan-online.com/images/15161-260401-0234_5.jpg"
    ],
    "price_original": 160160,
    "currency_code": "JPY",
    "brand_name": "Chrome Hearts",
    "gender_label": "メンズ",
    "general_category_name": "accessories",
    "category_name": "accessory",
    "subcategory_name": "ネックレス",
    "condition_rank": "B",
    "size_label": "20inch",
    "measurements_text": "チェーン幅0.2cm,全長52.5cm",
    "description": "素材: 925\n付属品: 国内配送の場合RINKAN購入証明書が付属します。※状態ランクC以下、シルバー・ゴールドパーツのない商品は除く",
    "parsed_at": "2026-04-16T00:42:12.070862+00:00"
  },
  {
    "title": "シルバーゴールドコンビチャームネックレストップ",
    "source_product_id": "15162-251205-0173",
    "product_url": "https://www.rinkan-online.com/products/15162-251205-0173",
    "main_image_url": "https://cdn.rinkan-online.com/images/15162-251205-0173_1.jpg",
    "image_urls": [
      "https://cdn.rinkan-online.com/images/15162-251205-0173_1.jpg",
      "https://cdn.rinkan-online.com/images/15162-251205-0173_2.jpg",
      "https://cdn.rinkan-online.com/images/15162-251205-0173_3.jpg",
      "https://cdn.rinkan-online.com/images/15162-251205-0173_4.jpg",
      "https://cdn.rinkan-online.com/images/15162-251205-0173_5.jpg"
    ],
    "price_original": 514800,
    "currency_code": "JPY",
    "brand_name": "Chrome Hearts",
    "gender_label": "メンズ",
    "general_category_name": "accessories",
    "category_name": "accessory",
    "subcategory_name": "ペンダントトップ",
    "condition_rank": "B",
    "size_label": null,
    "measurements_text": "横2cm,縦3cm",
    "description": "素材: 925 22K\n付属品: 国内配送の場合RINKAN購入証明書が付属します。※状態ランクC以下、シルバー・ゴールドパーツのない商品は除く",
    "parsed_at": "2026-04-16T00:42:12.887060+00:00"
  },
  {
    "title": "カモ柄ファイヤーマンジャケットブルゾン",
    "source_product_id": "10210-260213-0051",
    "product_url": "https://www.rinkan-online.com/products/10210-260213-0051",
    "main_image_url": "https://cdn.rinkan-online.com/images/10210-260213-0051_1.jpg",
    "image_urls": [
      "https://cdn.rinkan-online.com/images/10210-260213-0051_1.jpg",
      "https://cdn.rinkan-online.com/images/10210-260213-0051_2.jpg",
      "https://cdn.rinkan-online.com/images/10210-260213-0051_3.jpg"
    ],
    "price_original": 46750,
    "currency_code": "JPY",
    "brand_name": "THUG CLUB",
    "gender_label": "メンズ",
    "general_category_name": "wear",
    "category_name": "outerwear",
    "subcategory_name": "ブルゾン",
    "condition_rank": "A",
    "size_label": "4",
    "measurements_text": "肩幅55cm,身幅59cm,着丈71cm,袖丈68cm",
    "description": "素材: (表地) ポリエステル80%、コットン20% (表地2) ナイロン (裏地) ポリエステル",
    "parsed_at": "2026-04-16T00:42:13.601565+00:00"
  },
  {
    "title": "ロゴプリント2WAYレザーショルダートートバッグ",
    "source_product_id": "15050-260325-0132",
    "product_url": "https://www.rinkan-online.com/products/15050-260325-0132",
    "main_image_url": "https://cdn.rinkan-online.com/images/15050-260325-0132_1.jpg",
    "image_urls": [
      "https://cdn.rinkan-online.com/images/15050-260325-0132_1.jpg",
      "https://cdn.rinkan-online.com/images/15050-260325-0132_2.jpg",
      "https://cdn.rinkan-online.com/images/15050-260325-0132_3.jpg",
      "https://cdn.rinkan-online.com/images/15050-260325-0132_4.jpg",
      "https://cdn.rinkan-online.com/images/15050-260325-0132_5.jpg"
    ],
    "price_original": 34650,
    "currency_code": "JPY",
    "brand_name": "BALENCIAGA",
    "gender_label": "メンズ",
    "general_category_name": "bags",
    "category_name": "bag",
    "subcategory_name": "トートバッグ",
    "condition_rank": "C",
    "size_label": "XS",
    "measurements_text": "横最大34cm,縦26cm,マチ11cm,持ち手54cm,肩紐115cm前後調節可",
    "description": "素材: 表記なし\n付属品: 袋",
    "parsed_at": "2026-04-16T00:42:14.322248+00:00"
  },
  {
    "title": "レザートートバッグ",
    "source_product_id": "15050-260308-0085",
    "product_url": "https://www.rinkan-online.com/products/15050-260308-0085",
    "main_image_url": "https://cdn.rinkan-online.com/images/15050-260308-0085_1.jpg",
    "image_urls": [
      "https://cdn.rinkan-online.com/images/15050-260308-0085_1.jpg",
      "https://cdn.rinkan-online.com/images/15050-260308-0085_2.jpg",
      "https://cdn.rinkan-online.com/images/15050-260308-0085_3.jpg",
      "https://cdn.rinkan-online.com/images/15050-260308-0085_4.jpg",
      "https://cdn.rinkan-online.com/images/15050-260308-0085_5.jpg"
    ],
    "price_original": 34650,
    "currency_code": "JPY",
    "brand_name": "CELINE",
    "gender_label": "メンズ",
    "general_category_name": "bags",
    "category_name": "bag",
    "subcategory_name": "トートバッグ",
    "condition_rank": "C",
    "size_label": null,
    "measurements_text": "横53cm,縦31cm,マチ17cm,持ち手46cm",
    "description": "素材: 表記なし",
    "parsed_at": "2026-04-16T00:42:15.036476+00:00"
  },
  {
    "title": "シグネチャーレザートートバッグ",
    "source_product_id": "15050-260311-0131",
    "product_url": "https://www.rinkan-online.com/products/15050-260311-0131",
    "main_image_url": "https://cdn.rinkan-online.com/images/15050-260311-0131_1.jpg",
    "image_urls": [
      "https://cdn.rinkan-online.com/images/15050-260311-0131_1.jpg",
      "https://cdn.rinkan-online.com/images/15050-260311-0131_2.jpg",
      "https://cdn.rinkan-online.com/images/15050-260311-0131_3.jpg",
      "https://cdn.rinkan-online.com/images/15050-260311-0131_4.jpg",
      "https://cdn.rinkan-online.com/images/15050-260311-0131_5.jpg"
    ],
    "price_original": 28820,
    "currency_code": "JPY",
    "brand_name": "Rick Owens",
    "gender_label": "メンズ",
    "general_category_name": "bags",
    "category_name": "bag",
    "subcategory_name": "トートバッグ",
    "condition_rank": "B",
    "size_label": null,
    "measurements_text": "横34.5cm,縦43cm,持ち手58cm",
    "description": "素材: 表記なし",
    "parsed_at": "2026-04-16T00:42:15.746891+00:00"
  },
  {
    "title": "【お買い得アイテム】マルチジップボーダーパーカー",
    "source_product_id": "10625-260116-0163",
    "product_url": "https://www.rinkan-online.com/products/10625-260116-0163",
    "main_image_url": "https://cdn.rinkan-online.com/images/10625-260116-0163_1.jpg",
    "image_urls": [
      "https://cdn.rinkan-online.com/images/10625-260116-0163_1.jpg",
      "https://cdn.rinkan-online.com/images/10625-260116-0163_2.jpg",
      "https://cdn.rinkan-online.com/images/10625-260116-0163_3.jpg"
    ],
    "price_original": 22440,
    "currency_code": "JPY",
    "brand_name": "Burberry",
    "gender_label": "メンズ",
    "general_category_name": "wear",
    "category_name": "sweater",
    "subcategory_name": "パーカ",
    "condition_rank": "B",
    "size_label": "XS",
    "measurements_text": "裄丈90cm,身幅60cm,着丈69cm",
    "description": "素材: コットン",
    "parsed_at": "2026-04-16T00:42:16.561446+00:00"
  },
  {
    "title": "蛇腹レザークラッシュ加工スキニーデニムパンツ",
    "source_product_id": "10831-260224-0091",
    "product_url": "https://www.rinkan-online.com/products/10831-260224-0091",
    "main_image_url": "https://cdn.rinkan-online.com/images/10831-260224-0091_1.jpg",
    "image_urls": [
      "https://cdn.rinkan-online.com/images/10831-260224-0091_1.jpg",
      "https://cdn.rinkan-online.com/images/10831-260224-0091_2.jpg",
      "https://cdn.rinkan-online.com/images/10831-260224-0091_3.jpg"
    ],
    "price_original": 49280,
    "currency_code": "JPY",
    "brand_name": "AMIRI",
    "gender_label": "メンズ",
    "general_category_name": "wear",
    "category_name": "pants",
    "subcategory_name": "デニムパンツ",
    "condition_rank": "B",
    "size_label": "29インチ",
    "measurements_text": "ウエスト幅38cm,股上25cm,ワタリ幅26cm,股下84cm,裾幅14cm",
    "description": "素材: コットン98%、エラスタン2%",
    "parsed_at": "2026-04-16T00:42:17.280560+00:00"
  },
  {
    "title": "G金具 クシュベルハンドバッグ",
    "source_product_id": "35051-260405-0015",
    "product_url": "https://www.rinkan-online.com/products/35051-260405-0015",
    "main_image_url": "https://cdn.rinkan-online.com/images/35051-260405-0015_1.jpg",
    "image_urls": [
      "https://cdn.rinkan-online.com/images/35051-260405-0015_1.jpg",
      "https://cdn.rinkan-online.com/images/35051-260405-0015_2.jpg",
      "https://cdn.rinkan-online.com/images/35051-260405-0015_3.jpg",
      "https://cdn.rinkan-online.com/images/35051-260405-0015_4.jpg",
      "https://cdn.rinkan-online.com/images/35051-260405-0015_5.jpg"
    ],
    "price_original": 1617000,
    "currency_code": "JPY",
    "brand_name": "HERMES",
    "gender_label": "ユニセックス",
    "general_category_name": "bags",
    "category_name": "bag",
    "subcategory_name": "ハンドバッグ",
    "condition_rank": "B",
    "size_label": null,
    "measurements_text": "横38cm,縦30cm,マチ20cm,持ち手34cm",
    "description": "素材: 表記なし",
    "parsed_at": "2026-04-16T00:42:17.987916+00:00"
  },
  {
    "title": "モノグラムグラデーションデニム長袖シャツ 20SS",
    "source_product_id": "10312-260128-0324",
    "product_url": "https://www.rinkan-online.com/products/10312-260128-0324",
    "main_image_url": "https://cdn.rinkan-online.com/images/10312-260128-0324_1.jpg",
    "image_urls": [
      "https://cdn.rinkan-online.com/images/10312-260128-0324_1.jpg",
      "https://cdn.rinkan-online.com/images/10312-260128-0324_2.jpg",
      "https://cdn.rinkan-online.com/images/10312-260128-0324_3.jpg"
    ],
    "price_original": 207900,
    "currency_code": "JPY",
    "brand_name": "LOUIS VUITTON",
    "gender_label": "メンズ",
    "general_category_name": "wear",
    "category_name": "shirts",
    "subcategory_name": "ロングスリーブシャツ",
    "condition_rank": "B",
    "size_label": "M",
    "measurements_text": "肩幅47cm,身幅56cm,着丈70cm,袖丈65.5cm",
    "description": "素材: コットン",
    "parsed_at": "2026-04-16T00:42:18.856380+00:00"
  },
  {
    "title": "MAトラックジャケットブルゾン",
    "source_product_id": "10210-260302-0381",
    "product_url": "https://www.rinkan-online.com/products/10210-260302-0381",
    "main_image_url": "https://cdn.rinkan-online.com/images/10210-260302-0381_1.jpg",
    "image_urls": [
      "https://cdn.rinkan-online.com/images/10210-260302-0381_1.jpg",
      "https://cdn.rinkan-online.com/images/10210-260302-0381_2.jpg",
      "https://cdn.rinkan-online.com/images/10210-260302-0381_3.jpg"
    ],
    "price_original": 117040,
    "currency_code": "JPY",
    "brand_name": "AMIRI",
    "gender_label": "メンズ",
    "general_category_name": "wear",
    "category_name": "outerwear",
    "subcategory_name": "ブルゾン",
    "condition_rank": "A",
    "size_label": "S",
    "measurements_text": "肩幅49cm,身幅52cm,着丈58cm,袖丈65.5cm",
    "description": "素材: (表地) ポリエステル55%、コットン45% (裏地) レーヨン (リブ) ポリエステル\n付属品: タグ",
    "parsed_at": "2026-04-16T00:42:19.586727+00:00"
  },
  {
    "title": "テクニカルジャージートラックジャケットブルゾン",
    "source_product_id": "10210-260329-0296",
    "product_url": "https://www.rinkan-online.com/products/10210-260329-0296",
    "main_image_url": "https://cdn.rinkan-online.com/images/10210-260329-0296_1.jpg",
    "image_urls": [
      "https://cdn.rinkan-online.com/images/10210-260329-0296_1.jpg",
      "https://cdn.rinkan-online.com/images/10210-260329-0296_2.jpg",
      "https://cdn.rinkan-online.com/images/10210-260329-0296_3.jpg"
    ],
    "price_original": 92400,
    "currency_code": "JPY",
    "brand_name": "GUCCI",
    "gender_label": "メンズ",
    "general_category_name": "wear",
    "category_name": "outerwear",
    "subcategory_name": "ブルゾン",
    "condition_rank": "B",
    "size_label": "S",
    "measurements_text": "肩幅45cm,身幅46cm,着丈57cm,袖丈63cm",
    "description": "素材: (表地) レーヨン86%、ナイロン10%、ポリウレタン4% (別布) コットン (刺繍) ポリエステル",
    "parsed_at": "2026-04-16T00:42:20.316734+00:00"
  },
  {
    "title": "PAVEダイヤ/ペンダント/ゴールドネックレストップ",
    "source_product_id": "15162-260412-0222",
    "product_url": "https://www.rinkan-online.com/products/15162-260412-0222",
    "main_image_url": "https://cdn.rinkan-online.com/images/15162-260412-0222_1.jpg",
    "image_urls": [
      "https://cdn.rinkan-online.com/images/15162-260412-0222_1.jpg",
      "https://cdn.rinkan-online.com/images/15162-260412-0222_2.jpg",
      "https://cdn.rinkan-online.com/images/15162-260412-0222_3.jpg",
      "https://cdn.rinkan-online.com/images/15162-260412-0222_4.jpg",
      "https://cdn.rinkan-online.com/images/15162-260412-0222_5.jpg"
    ],
    "price_original": 2266000,
    "currency_code": "JPY",
    "brand_name": "Chrome Hearts",
    "gender_label": "メンズ",
    "general_category_name": "accessories",
    "category_name": "accessory",
    "subcategory_name": "ペンダントトップ",
    "condition_rank": "B",
    "size_label": null,
    "measurements_text": "横1.6cm,縦3.3cm",
    "description": "素材: 22K\n付属品: 国内配送の場合RINKAN購入証明書が付属します。※状態ランクC以下、シルバー・ゴールドパーツのない商品は除く",
    "parsed_at": "2026-04-16T00:42:21.022591+00:00"
  },
  {
    "title": "MATTY BOYバックプリントプルオーバーパーカー",
    "source_product_id": "10625-260408-0290",
    "product_url": "https://www.rinkan-online.com/products/10625-260408-0290",
    "main_image_url": "https://cdn.rinkan-online.com/images/10625-260408-0290_1.jpg",
    "image_urls": [
      "https://cdn.rinkan-online.com/images/10625-260408-0290_1.jpg",
      "https://cdn.rinkan-online.com/images/10625-260408-0290_2.jpg",
      "https://cdn.rinkan-online.com/images/10625-260408-0290_3.jpg"
    ],
    "price_original": 125840,
    "currency_code": "JPY",
    "brand_name": "Chrome Hearts",
    "gender_label": "メンズ",
    "general_category_name": "wear",
    "category_name": "sweater",
    "subcategory_name": "パーカ",
    "condition_rank": "B",
    "size_label": "L",
    "measurements_text": "肩幅60cm,身幅66.5cm,着丈71cm,袖丈70cm",
    "description": "素材: (表地) コットン (リブ) コットン95%、ポリウレタン5%\n付属品: 国内配送の場合RINKAN購入証明書が付属します。※状態ランクC以下、シルバー・ゴールドパーツのない商品は除く",
    "parsed_at": "2026-04-16T00:42:21.816675+00:00"
  },
  {
    "title": "レザーフリンジ&スタッズデニムジャケット",
    "source_product_id": "10207-260205-0362",
    "product_url": "https://www.rinkan-online.com/products/10207-260205-0362",
    "main_image_url": "https://cdn.rinkan-online.com/images/10207-260205-0362_1.jpg",
    "image_urls": [
      "https://cdn.rinkan-online.com/images/10207-260205-0362_1.jpg",
      "https://cdn.rinkan-online.com/images/10207-260205-0362_2.jpg",
      "https://cdn.rinkan-online.com/images/10207-260205-0362_3.jpg"
    ],
    "price_original": 104720,
    "currency_code": "JPY",
    "brand_name": "RAF SIMONS",
    "gender_label": "メンズ",
    "general_category_name": "wear",
    "category_name": "outerwear",
    "subcategory_name": "デニムジャケット",
    "condition_rank": "B",
    "size_label": "S",
    "measurements_text": "裄丈95.5cm,身幅81cm,着丈83cm",
    "description": "素材: コットン",
    "parsed_at": "2026-04-16T00:42:22.618694+00:00"
  },
  {
    "title": "ロゴプリントヴィンテージ加工Tシャツ",
    "source_product_id": "10519-260408-0008",
    "product_url": "https://www.rinkan-online.com/products/10519-260408-0008",
    "main_image_url": "https://cdn.rinkan-online.com/images/10519-260408-0008_1.jpg",
    "image_urls": [
      "https://cdn.rinkan-online.com/images/10519-260408-0008_1.jpg",
      "https://cdn.rinkan-online.com/images/10519-260408-0008_2.jpg",
      "https://cdn.rinkan-online.com/images/10519-260408-0008_3.jpg"
    ],
    "price_original": 46200,
    "currency_code": "JPY",
    "brand_name": "ACNE STUDIOS",
    "gender_label": "メンズ",
    "general_category_name": "wear",
    "category_name": "shirts",
    "subcategory_name": "Tシャツ",
    "condition_rank": "B",
    "size_label": "L",
    "measurements_text": "肩幅52cm,身幅56.5cm,着丈70cm,袖丈24.5cm",
    "description": "素材: コットン85%、指定外繊維15%",
    "parsed_at": "2026-04-16T00:42:23.432548+00:00"
  },
  {
    "title": "CHELSEAY HOTELプリントTシャツ 26SS",
    "source_product_id": "10519-260402-0052",
    "product_url": "https://www.rinkan-online.com/products/10519-260402-0052",
    "main_image_url": "https://cdn.rinkan-online.com/images/10519-260402-0052_1.jpg",
    "image_urls": [
      "https://cdn.rinkan-online.com/images/10519-260402-0052_1.jpg",
      "https://cdn.rinkan-online.com/images/10519-260402-0052_2.jpg",
      "https://cdn.rinkan-online.com/images/10519-260402-0052_3.jpg"
    ],
    "price_original": 61600,
    "currency_code": "JPY",
    "brand_name": "Paly Hollywood",
    "gender_label": "メンズ",
    "general_category_name": "wear",
    "category_name": "shirts",
    "subcategory_name": "Tシャツ",
    "condition_rank": "N",
    "size_label": "L",
    "measurements_text": "裄丈49.5cm,身幅68.5cm,着丈64.5cm",
    "description": "素材: コットン\n付属品: タグ\nその他特徴: 画像と実物のダメージの配置が多少異なる場合があります",
    "parsed_at": "2026-04-16T00:42:24.131306+00:00"
  },
  {
    "title": "シルバーネックレス",
    "source_product_id": "15161-260111-0227",
    "product_url": "https://www.rinkan-online.com/products/15161-260111-0227",
    "main_image_url": "https://cdn.rinkan-online.com/images/15161-260111-0227_1.jpg",
    "image_urls": [
      "https://cdn.rinkan-online.com/images/15161-260111-0227_1.jpg",
      "https://cdn.rinkan-online.com/images/15161-260111-0227_2.jpg",
      "https://cdn.rinkan-online.com/images/15161-260111-0227_3.jpg",
      "https://cdn.rinkan-online.com/images/15161-260111-0227_4.jpg",
      "https://cdn.rinkan-online.com/images/15161-260111-0227_5.jpg"
    ],
    "price_original": 400400,
    "currency_code": "JPY",
    "brand_name": "Chrome Hearts",
    "gender_label": "メンズ",
    "general_category_name": "accessories",
    "category_name": "accessory",
    "subcategory_name": "ネックレス",
    "condition_rank": "B",
    "size_label": "20inch",
    "measurements_text": "チェーン幅0.5cm,全長51.5cm",
    "description": "素材: 925 14K\n付属品: 国内配送の場合RINKAN購入証明書が付属します。※状態ランクC以下、シルバー・ゴールドパーツのない商品は除く",
    "parsed_at": "2026-04-16T00:42:24.868769+00:00"
  },
  {
    "title": "ヴァインダガー袖英字長袖カットソー",
    "source_product_id": "10518-260317-0237",
    "product_url": "https://www.rinkan-online.com/products/10518-260317-0237",
    "main_image_url": "https://cdn.rinkan-online.com/images/10518-260317-0237_1.jpg",
    "image_urls": [
      "https://cdn.rinkan-online.com/images/10518-260317-0237_1.jpg",
      "https://cdn.rinkan-online.com/images/10518-260317-0237_2.jpg",
      "https://cdn.rinkan-online.com/images/10518-260317-0237_3.jpg"
    ],
    "price_original": 45760,
    "currency_code": "JPY",
    "brand_name": "Chrome Hearts",
    "gender_label": "メンズ",
    "general_category_name": "wear",
    "category_name": "shirts",
    "subcategory_name": "ロングスリーブカットソー",
    "condition_rank": "B",
    "size_label": "M",
    "measurements_text": "肩幅43cm,身幅48cm,着丈66cm,袖丈65cm",
    "description": "素材: コットン\n付属品: 国内配送の場合RINKAN購入証明書が付属します。※状態ランクC以下、シルバー・ゴールドパーツのない商品は除く",
    "parsed_at": "2026-04-16T00:42:25.602015+00:00"
  },
  {
    "title": "シルバーネックレス",
    "source_product_id": "15161-260206-0198",
    "product_url": "https://www.rinkan-online.com/products/15161-260206-0198",
    "main_image_url": "https://cdn.rinkan-online.com/images/15161-260206-0198_1.jpg",
    "image_urls": [
      "https://cdn.rinkan-online.com/images/15161-260206-0198_1.jpg",
      "https://cdn.rinkan-online.com/images/15161-260206-0198_2.jpg",
      "https://cdn.rinkan-online.com/images/15161-260206-0198_3.jpg",
      "https://cdn.rinkan-online.com/images/15161-260206-0198_4.jpg",
      "https://cdn.rinkan-online.com/images/15161-260206-0198_5.jpg"
    ],
    "price_original": 400400,
    "currency_code": "JPY",
    "brand_name": "Chrome Hearts",
    "gender_label": "メンズ",
    "general_category_name": "accessories",
    "category_name": "accessory",
    "subcategory_name": "ネックレス",
    "condition_rank": "B",
    "size_label": "20inch",
    "measurements_text": "チェーン幅0.5cm,全長51.5cm",
    "description": "素材: 925 14K\n付属品: 国内配送の場合RINKAN購入証明書が付属します。※状態ランクC以下、シルバー・ゴールドパーツのない商品は除く",
    "parsed_at": "2026-04-16T00:42:26.306586+00:00"
  },
  {
    "title": "フラワープリントTシャツ",
    "source_product_id": "10519-260402-0050",
    "product_url": "https://www.rinkan-online.com/products/10519-260402-0050",
    "main_image_url": "https://cdn.rinkan-online.com/images/10519-260402-0050_1.jpg",
    "image_urls": [
      "https://cdn.rinkan-online.com/images/10519-260402-0050_1.jpg",
      "https://cdn.rinkan-online.com/images/10519-260402-0050_2.jpg",
      "https://cdn.rinkan-online.com/images/10519-260402-0050_3.jpg"
    ],
    "price_original": 18480,
    "currency_code": "JPY",
    "brand_name": "ANN DEMEULEMEESTER",
    "gender_label": "メンズ",
    "general_category_name": "wear",
    "category_name": "shirts",
    "subcategory_name": "Tシャツ",
    "condition_rank": "B",
    "size_label": "S",
    "measurements_text": "肩幅54cm,身幅59cm,着丈63cm,袖丈26cm",
    "description": "素材: コットン",
    "parsed_at": "2026-04-16T00:42:27.017086+00:00"
  },
  {
    "title": "フローラルテンプル眼鏡",
    "source_product_id": "15270-260228-0397",
    "product_url": "https://www.rinkan-online.com/products/15270-260228-0397",
    "main_image_url": "https://cdn.rinkan-online.com/images/15270-260228-0397_1.jpg",
    "image_urls": [
      "https://cdn.rinkan-online.com/images/15270-260228-0397_1.jpg",
      "https://cdn.rinkan-online.com/images/15270-260228-0397_2.jpg",
      "https://cdn.rinkan-online.com/images/15270-260228-0397_3.jpg"
    ],
    "price_original": 171600,
    "currency_code": "JPY",
    "brand_name": "Chrome Hearts",
    "gender_label": "メンズ",
    "general_category_name": "goods",
    "category_name": "goods",
    "subcategory_name": "メガネ",
    "condition_rank": "B",
    "size_label": null,
    "measurements_text": "横14.3cm,縦4.5cm,アーム13cm",
    "description": "素材: 表記なし\n付属品: ケース\n国内配送の場合RINKAN購入証明書が付属します。※状態ランクC以下、シルバー・ゴールドパーツのない商品は除く",
    "parsed_at": "2026-04-16T00:42:27.851450+00:00"
  },
  {
    "title": "シルバーネックレストップ",
    "source_product_id": "15162-260323-0426",
    "product_url": "https://www.rinkan-online.com/products/15162-260323-0426",
    "main_image_url": "https://cdn.rinkan-online.com/images/15162-260323-0426_1.jpg",
    "image_urls": [
      "https://cdn.rinkan-online.com/images/15162-260323-0426_1.jpg",
      "https://cdn.rinkan-online.com/images/15162-260323-0426_2.jpg",
      "https://cdn.rinkan-online.com/images/15162-260323-0426_3.jpg",
      "https://cdn.rinkan-online.com/images/15162-260323-0426_4.jpg",
      "https://cdn.rinkan-online.com/images/15162-260323-0426_5.jpg"
    ],
    "price_original": 171600,
    "currency_code": "JPY",
    "brand_name": "Chrome Hearts",
    "gender_label": "メンズ",
    "general_category_name": "accessories",
    "category_name": "accessory",
    "subcategory_name": "ペンダントトップ",
    "condition_rank": "B",
    "size_label": null,
    "measurements_text": "横1.1cm,縦1.7cm",
    "description": "素材: 925\n付属品: 国内配送の場合RINKAN購入証明書が付属します。※状態ランクC以下、シルバー・ゴールドパーツのない商品は除く",
    "parsed_at": "2026-04-16T00:42:28.661636+00:00"
  },
  {
    "title": "シルバーネックレス",
    "source_product_id": "15161-260327-0358",
    "product_url": "https://www.rinkan-online.com/products/15161-260327-0358",
    "main_image_url": "https://cdn.rinkan-online.com/images/15161-260327-0358_1.jpg",
    "image_urls": [
      "https://cdn.rinkan-online.com/images/15161-260327-0358_1.jpg",
      "https://cdn.rinkan-online.com/images/15161-260327-0358_2.jpg",
      "https://cdn.rinkan-online.com/images/15161-260327-0358_3.jpg",
      "https://cdn.rinkan-online.com/images/15161-260327-0358_4.jpg",
      "https://cdn.rinkan-online.com/images/15161-260327-0358_5.jpg"
    ],
    "price_original": 114400,
    "currency_code": "JPY",
    "brand_name": "Chrome Hearts",
    "gender_label": "メンズ",
    "general_category_name": "accessories",
    "category_name": "accessory",
    "subcategory_name": "ネックレス",
    "condition_rank": "B",
    "size_label": "18inch",
    "measurements_text": "チェーン幅0.2cm,全長47cm",
    "description": "素材: 925\n付属品: 国内配送の場合RINKAN購入証明書が付属します。※状態ランクC以下、シルバー・ゴールドパーツのない商品は除く",
    "parsed_at": "2026-04-16T00:42:29.383446+00:00"
  },
  {
    "title": "ケルティックボタンレザーウォレット財布",
    "source_product_id": "15268-260116-0275",
    "product_url": "https://www.rinkan-online.com/products/15268-260116-0275",
    "main_image_url": "https://cdn.rinkan-online.com/images/15268-260116-0275_1.jpg",
    "image_urls": [
      "https://cdn.rinkan-online.com/images/15268-260116-0275_1.jpg",
      "https://cdn.rinkan-online.com/images/15268-260116-0275_2.jpg",
      "https://cdn.rinkan-online.com/images/15268-260116-0275_3.jpg"
    ],
    "price_original": 114400,
    "currency_code": "JPY",
    "brand_name": "Chrome Hearts",
    "gender_label": "メンズ",
    "general_category_name": "goods",
    "category_name": "goods",
    "subcategory_name": "財布",
    "condition_rank": "B",
    "size_label": null,
    "measurements_text": "横14.5cm,縦9cm",
    "description": "素材: 表記なし\n付属品: 国内配送の場合RINKAN購入証明書が付属します。※状態ランクC以下、シルバー・ゴールドパーツのない商品は除く\nその他特徴: 小銭入れ×1、札入れ×1、カード入れ×1",
    "parsed_at": "2026-04-16T00:42:30.233438+00:00"
  },
  {
    "title": "ラージドッグタグネックレストップ",
    "source_product_id": "15162-241126-0315",
    "product_url": "https://www.rinkan-online.com/products/15162-241126-0315",
    "main_image_url": "https://cdn.rinkan-online.com/images/15162-241126-0315_1.jpg",
    "image_urls": [
      "https://cdn.rinkan-online.com/images/15162-241126-0315_1.jpg",
      "https://cdn.rinkan-online.com/images/15162-241126-0315_2.jpg",
      "https://cdn.rinkan-online.com/images/15162-241126-0315_3.jpg",
      "https://cdn.rinkan-online.com/images/15162-241126-0315_4.jpg",
      "https://cdn.rinkan-online.com/images/15162-241126-0315_5.jpg"
    ],
    "price_original": 160160,
    "currency_code": "JPY",
    "brand_name": "Chrome Hearts",
    "gender_label": "メンズ",
    "general_category_name": "accessories",
    "category_name": "accessory",
    "subcategory_name": "ペンダントトップ",
    "condition_rank": "B",
    "size_label": null,
    "measurements_text": "横2.9cm,縦5.6cm",
    "description": "素材: 925\n付属品: 国内配送の場合RINKAN購入証明書が付属します。※状態ランクC以下、シルバー・ゴールドパーツのない商品は除く",
    "parsed_at": "2026-04-16T00:42:30.942745+00:00"
  },
  {
    "title": "シルバーリング",
    "source_product_id": "15160-260318-0271",
    "product_url": "https://www.rinkan-online.com/products/15160-260318-0271",
    "main_image_url": "https://cdn.rinkan-online.com/images/15160-260318-0271_1.jpg",
    "image_urls": [
      "https://cdn.rinkan-online.com/images/15160-260318-0271_1.jpg",
      "https://cdn.rinkan-online.com/images/15160-260318-0271_2.jpg",
      "https://cdn.rinkan-online.com/images/15160-260318-0271_3.jpg",
      "https://cdn.rinkan-online.com/images/15160-260318-0271_4.jpg",
      "https://cdn.rinkan-online.com/images/15160-260318-0271_5.jpg"
    ],
    "price_original": 434720,
    "currency_code": "JPY",
    "brand_name": "Chrome Hearts",
    "gender_label": "メンズ",
    "general_category_name": "accessories",
    "category_name": "accessory",
    "subcategory_name": "リング",
    "condition_rank": "B",
    "size_label": "16号",
    "measurements_text": "-",
    "description": "素材: 925\n付属品: 国内配送の場合RINKAN購入証明書が付属します。※状態ランクC以下、シルバー・ゴールドパーツのない商品は除く",
    "parsed_at": "2026-04-16T00:42:31.657337+00:00"
  },
  {
    "title": "【クロムハーツお買い得価格】シルバーマグネット",
    "source_product_id": "15278-250221-0217",
    "product_url": "https://www.rinkan-online.com/products/15278-250221-0217",
    "main_image_url": "https://cdn.rinkan-online.com/images/15278-250221-0217_1.jpg",
    "image_urls": [
      "https://cdn.rinkan-online.com/images/15278-250221-0217_1.jpg",
      "https://cdn.rinkan-online.com/images/15278-250221-0217_2.jpg",
      "https://cdn.rinkan-online.com/images/15278-250221-0217_3.jpg",
      "https://cdn.rinkan-online.com/images/15278-250221-0217_4.jpg",
      "https://cdn.rinkan-online.com/images/15278-250221-0217_5.jpg"
    ],
    "price_original": 24200,
    "currency_code": "JPY",
    "brand_name": "Chrome Hearts",
    "gender_label": "メンズ",
    "general_category_name": null,
    "category_name": "goods",
    "subcategory_name": "その他グッズ",
    "condition_rank": "B",
    "size_label": null,
    "measurements_text": "横2.8cm,縦3cm",
    "description": "素材: 925\n付属品: 国内配送の場合RINKAN購入証明書が付属します。※状態ランクC以下、シルバー・ゴールドパーツのない商品は除く",
    "parsed_at": "2026-04-16T00:42:32.388046+00:00"
  },
  {
    "title": "マイアミ限定ホースシュープルオーバーパーカー",
    "source_product_id": "10625-240717-0042",
    "product_url": "https://www.rinkan-online.com/products/10625-240717-0042",
    "main_image_url": "https://cdn.rinkan-online.com/images/10625-240717-0042_1.jpg",
    "image_urls": [
      "https://cdn.rinkan-online.com/images/10625-240717-0042_1.jpg",
      "https://cdn.rinkan-online.com/images/10625-240717-0042_2.jpg",
      "https://cdn.rinkan-online.com/images/10625-240717-0042_3.jpg"
    ],
    "price_original": 154000,
    "currency_code": "JPY",
    "brand_name": "Chrome Hearts",
    "gender_label": "メンズ",
    "general_category_name": "wear",
    "category_name": "sweater",
    "subcategory_name": "パーカ",
    "condition_rank": "A",
    "size_label": "M",
    "measurements_text": "肩幅56cm,身幅60cm,着丈68.5cm,袖丈70.5cm",
    "description": "素材: コットン\n付属品: 国内配送の場合RINKAN購入証明書が付属します。※状態ランクC以下、シルバー・ゴールドパーツのない商品は除く",
    "parsed_at": "2026-04-16T00:42:33.147604+00:00"
  },
  {
    "title": "モノグラムグラディエントTシャツ 20AW",
    "source_product_id": "10519-260407-0268",
    "product_url": "https://www.rinkan-online.com/products/10519-260407-0268",
    "main_image_url": "https://cdn.rinkan-online.com/images/10519-260407-0268_1.jpg",
    "image_urls": [
      "https://cdn.rinkan-online.com/images/10519-260407-0268_1.jpg",
      "https://cdn.rinkan-online.com/images/10519-260407-0268_2.jpg",
      "https://cdn.rinkan-online.com/images/10519-260407-0268_3.jpg"
    ],
    "price_original": 92400,
    "currency_code": "JPY",
    "brand_name": "LOUISVUITTON",
    "gender_label": "メンズ",
    "general_category_name": "wear",
    "category_name": "shirts",
    "subcategory_name": "Tシャツ",
    "condition_rank": "B",
    "size_label": "L",
    "measurements_text": "肩幅47cm,身幅54.5cm,着丈65cm,袖丈19.5cm",
    "description": "素材: コットン",
    "parsed_at": "2026-04-16T00:42:34.092284+00:00"
  },
  {
    "title": "デジタルカモマウンテンパーカーブルゾン 24SS",
    "source_product_id": "10210-260412-0103",
    "product_url": "https://www.rinkan-online.com/products/10210-260412-0103",
    "main_image_url": "https://cdn.rinkan-online.com/images/10210-260412-0103_1.jpg",
    "image_urls": [
      "https://cdn.rinkan-online.com/images/10210-260412-0103_1.jpg",
      "https://cdn.rinkan-online.com/images/10210-260412-0103_2.jpg",
      "https://cdn.rinkan-online.com/images/10210-260412-0103_3.jpg"
    ],
    "price_original": 196350,
    "currency_code": "JPY",
    "brand_name": "LOUISVUITTON",
    "gender_label": "メンズ",
    "general_category_name": "wear",
    "category_name": "outerwear",
    "subcategory_name": "ブルゾン",
    "condition_rank": "A",
    "size_label": "54",
    "measurements_text": "肩幅57cm,身幅71cm,着丈74cm,袖丈67.5cm",
    "description": "素材: コットン",
    "parsed_at": "2026-04-16T00:42:34.812136+00:00"
  },
  {
    "title": "カシミアニットドレープトレンカロングパンツ 22AW",
    "source_product_id": "50829-260412-0129",
    "product_url": "https://www.rinkan-online.com/products/50829-260412-0129",
    "main_image_url": "https://cdn.rinkan-online.com/images/50829-260412-0129_1.jpg",
    "image_urls": [
      "https://cdn.rinkan-online.com/images/50829-260412-0129_1.jpg",
      "https://cdn.rinkan-online.com/images/50829-260412-0129_2.jpg",
      "https://cdn.rinkan-online.com/images/50829-260412-0129_3.jpg"
    ],
    "price_original": 86240,
    "currency_code": "JPY",
    "brand_name": "LOUISVUITTON",
    "gender_label": "レディース",
    "general_category_name": "wear",
    "category_name": "pants",
    "subcategory_name": "ロングパンツ",
    "condition_rank": "B",
    "size_label": "M",
    "measurements_text": "ウエスト幅33cm,股上40cm,ワタリ幅36cm,股下78cm,裾幅12cm",
    "description": "素材: カシミヤ98%、ナイロン1%、ポリウレタン1%",
    "parsed_at": "2026-04-16T00:42:35.736601+00:00"
  },
  {
    "title": "ダモフラージュテーラードジャケット 24SS",
    "source_product_id": "10211-260413-0004",
    "product_url": "https://www.rinkan-online.com/products/10211-260413-0004",
    "main_image_url": "https://cdn.rinkan-online.com/images/10211-260413-0004_1.jpg",
    "image_urls": [
      "https://cdn.rinkan-online.com/images/10211-260413-0004_1.jpg",
      "https://cdn.rinkan-online.com/images/10211-260413-0004_2.jpg",
      "https://cdn.rinkan-online.com/images/10211-260413-0004_3.jpg"
    ],
    "price_original": 231000,
    "currency_code": "JPY",
    "brand_name": "LOUISVUITTON",
    "gender_label": "メンズ",
    "general_category_name": "wear",
    "category_name": "outerwear",
    "subcategory_name": "その他ジャケット",
    "condition_rank": "B",
    "size_label": "52",
    "measurements_text": "肩幅48cm,身幅55cm,着丈72cm,袖丈65cm",
    "description": "素材: (表地) コットン99%、ポリエステル1% (裏地) キュプラ79%、コットン21%",
    "parsed_at": "2026-04-16T00:42:36.561747+00:00"
  },
  {
    "title": "AVIAKITライダースレザージャケット",
    "source_product_id": "10103-260413-0301",
    "product_url": "https://www.rinkan-online.com/products/10103-260413-0301",
    "main_image_url": "https://cdn.rinkan-online.com/images/10103-260413-0301_1.jpg",
    "image_urls": [
      "https://cdn.rinkan-online.com/images/10103-260413-0301_1.jpg",
      "https://cdn.rinkan-online.com/images/10103-260413-0301_2.jpg",
      "https://cdn.rinkan-online.com/images/10103-260413-0301_3.jpg"
    ],
    "price_original": 154000,
    "currency_code": "JPY",
    "brand_name": "Lewis Leathers",
    "gender_label": "メンズ",
    "general_category_name": "wear",
    "category_name": "outerwear",
    "subcategory_name": "レザージャケット",
    "condition_rank": "A",
    "size_label": "38",
    "measurements_text": "肩幅42.5cm,身幅52.5cm,着丈64.5cm,袖丈62cm",
    "description": "素材: (表地) 本革 (裏地) ポリエステル65%、コットン35% (袖裏) ビスコース",
    "parsed_at": "2026-04-16T00:42:37.382523+00:00"
  },
  {
    "title": "デザインランニングスニーカー",
    "source_product_id": "15379-260409-0169",
    "product_url": "https://www.rinkan-online.com/products/15379-260409-0169",
    "main_image_url": "https://cdn.rinkan-online.com/images/15379-260409-0169_1.jpg",
    "image_urls": [
      "https://cdn.rinkan-online.com/images/15379-260409-0169_1.jpg",
      "https://cdn.rinkan-online.com/images/15379-260409-0169_2.jpg",
      "https://cdn.rinkan-online.com/images/15379-260409-0169_3.jpg",
      "https://cdn.rinkan-online.com/images/15379-260409-0169_4.jpg",
      "https://cdn.rinkan-online.com/images/15379-260409-0169_5.jpg"
    ],
    "price_original": 24640,
    "currency_code": "JPY",
    "brand_name": "Y-3",
    "gender_label": "メンズ",
    "general_category_name": "shoes",
    "category_name": "shoes",
    "subcategory_name": "ローカットスニーカー",
    "condition_rank": "A",
    "size_label": "29cm",
    "measurements_text": "アウトソール横幅最大12cm,アウトソール全長34cm",
    "description": "素材: 表記なし\n付属品: 箱 タグ 替え紐",
    "parsed_at": "2026-04-16T00:42:38.118421+00:00"
  },
  {
    "title": "×NBA ロゴパッチテーラードジャケット 21AW",
    "source_product_id": "10211-260413-0003",
    "product_url": "https://www.rinkan-online.com/products/10211-260413-0003",
    "main_image_url": "https://cdn.rinkan-online.com/images/10211-260413-0003_1.jpg",
    "image_urls": [
      "https://cdn.rinkan-online.com/images/10211-260413-0003_1.jpg",
      "https://cdn.rinkan-online.com/images/10211-260413-0003_2.jpg",
      "https://cdn.rinkan-online.com/images/10211-260413-0003_3.jpg"
    ],
    "price_original": 103950,
    "currency_code": "JPY",
    "brand_name": "LOUISVUITTON",
    "gender_label": "メンズ",
    "general_category_name": "wear",
    "category_name": "outerwear",
    "subcategory_name": "その他ジャケット",
    "condition_rank": "B",
    "size_label": "50",
    "measurements_text": "肩幅51cm,身幅55cm,着丈81.5cm,袖丈63cm",
    "description": "素材: (表地) ウール59%、コットン37%、ナイロン4% (裏地) キュプラ74%、コットン26%",
    "parsed_at": "2026-04-16T00:42:38.829535+00:00"
  },
  {
    "title": "シルバーネックレストップ",
    "source_product_id": "15162-260327-0272",
    "product_url": "https://www.rinkan-online.com/products/15162-260327-0272",
    "main_image_url": "https://cdn.rinkan-online.com/images/15162-260327-0272_1.jpg",
    "image_urls": [
      "https://cdn.rinkan-online.com/images/15162-260327-0272_1.jpg",
      "https://cdn.rinkan-online.com/images/15162-260327-0272_2.jpg",
      "https://cdn.rinkan-online.com/images/15162-260327-0272_3.jpg",
      "https://cdn.rinkan-online.com/images/15162-260327-0272_4.jpg",
      "https://cdn.rinkan-online.com/images/15162-260327-0272_5.jpg"
    ],
    "price_original": 64020,
    "currency_code": "JPY",
    "brand_name": "LONEONES",
    "gender_label": "メンズ",
    "general_category_name": "accessories",
    "category_name": "accessory",
    "subcategory_name": "ペンダントトップ",
    "condition_rank": "B",
    "size_label": "L",
    "measurements_text": "横1.9cm,縦6.3cm",
    "description": "素材: 表記なし",
    "parsed_at": "2026-04-16T00:42:39.635406+00:00"
  },
  {
    "title": "パペットバックパックジップアップブルゾン 21SS",
    "source_product_id": "10210-260412-0054",
    "product_url": "https://www.rinkan-online.com/products/10210-260412-0054",
    "main_image_url": "https://cdn.rinkan-online.com/images/10210-260412-0054_1.jpg",
    "image_urls": [
      "https://cdn.rinkan-online.com/images/10210-260412-0054_1.jpg",
      "https://cdn.rinkan-online.com/images/10210-260412-0054_2.jpg",
      "https://cdn.rinkan-online.com/images/10210-260412-0054_3.jpg"
    ],
    "price_original": 115500,
    "currency_code": "JPY",
    "brand_name": "LOUISVUITTON",
    "gender_label": "メンズ",
    "general_category_name": "wear",
    "category_name": "outerwear",
    "subcategory_name": "ブルゾン",
    "condition_rank": "B",
    "size_label": "S",
    "measurements_text": "肩幅43cm,身幅53cm,着丈79cm,袖丈66cm",
    "description": "素材: (表地) コットン (中綿) ポリエステル\nその他特徴: 肩パッドが付いています",
    "parsed_at": "2026-04-16T00:42:40.383028+00:00"
  },
  {
    "title": "ミックスフリンジニット 23SS",
    "source_product_id": "10416-260412-0110",
    "product_url": "https://www.rinkan-online.com/products/10416-260412-0110",
    "main_image_url": "https://cdn.rinkan-online.com/images/10416-260412-0110_1.jpg",
    "image_urls": [
      "https://cdn.rinkan-online.com/images/10416-260412-0110_1.jpg",
      "https://cdn.rinkan-online.com/images/10416-260412-0110_2.jpg",
      "https://cdn.rinkan-online.com/images/10416-260412-0110_3.jpg"
    ],
    "price_original": 92400,
    "currency_code": "JPY",
    "brand_name": "LOUISVUITTON",
    "gender_label": "メンズ",
    "general_category_name": "wear",
    "category_name": "sweater",
    "subcategory_name": "セーター",
    "condition_rank": "B",
    "size_label": "M",
    "measurements_text": "肩幅48cm,身幅50cm,着丈68cm,袖丈61cm",
    "description": "素材: ウール29%、リネン29%、コットン29%、アルパカ12%、ポリアミド1%",
    "parsed_at": "2026-04-16T00:42:41.074630+00:00"
  },
  {
    "title": "エンボスロゴ刺繍ロングパンツ 23SS",
    "source_product_id": "10829-260413-0012",
    "product_url": "https://www.rinkan-online.com/products/10829-260413-0012",
    "main_image_url": "https://cdn.rinkan-online.com/images/10829-260413-0012_1.jpg",
    "image_urls": [
      "https://cdn.rinkan-online.com/images/10829-260413-0012_1.jpg",
      "https://cdn.rinkan-online.com/images/10829-260413-0012_2.jpg",
      "https://cdn.rinkan-online.com/images/10829-260413-0012_3.jpg"
    ],
    "price_original": 46200,
    "currency_code": "JPY",
    "brand_name": "LOUISVUITTON",
    "gender_label": "メンズ",
    "general_category_name": "wear",
    "category_name": "pants",
    "subcategory_name": "ロングパンツ",
    "condition_rank": "B",
    "size_label": "46",
    "measurements_text": "ウエスト幅42cm,股上33.5cm,ワタリ幅30cm,股下69cm,裾幅22cm",
    "description": "素材: (表地) コットン55%、ウール45% (裏地) コットン",
    "parsed_at": "2026-04-16T00:42:41.762822+00:00"
  },
  {
    "title": "フラワーエンブロイダリー再構築デニムパンツ",
    "source_product_id": "10831-260413-0103",
    "product_url": "https://www.rinkan-online.com/products/10831-260413-0103",
    "main_image_url": "https://cdn.rinkan-online.com/images/10831-260413-0103_1.jpg",
    "image_urls": [
      "https://cdn.rinkan-online.com/images/10831-260413-0103_1.jpg",
      "https://cdn.rinkan-online.com/images/10831-260413-0103_2.jpg",
      "https://cdn.rinkan-online.com/images/10831-260413-0103_3.jpg"
    ],
    "price_original": 73920,
    "currency_code": "JPY",
    "brand_name": "Ready made",
    "gender_label": "メンズ",
    "general_category_name": "wear",
    "category_name": "pants",
    "subcategory_name": "デニムパンツ",
    "condition_rank": "B",
    "size_label": null,
    "measurements_text": "ウエスト幅38cm,股上29cm,ワタリ幅30.5cm,股下66.5cm,裾幅25cm",
    "description": "素材: (表地) コットン (刺繍) キュプラ\nその他特徴: ボタンフライデザインです",
    "parsed_at": "2026-04-16T00:42:42.483152+00:00"
  }
]